mintomfig/__init__.py
mintomfig-0.3.0.dist-info/METADATA
mintomfig-0.3.0.dist-info/WHEEL
mintomfig-0.3.0.dist-info/RECORD
