Metadata-Version: 2.1
Name: mintomfig
Version: 0.3.0
Summary: 
Author: redthing1
Author-email: redthing1@alt.icu
Requires-Python: >=3.8,<4.0
Classifier: Programming Language :: Python :: 3
Classifier: Programming Language :: Python :: 3.8
Classifier: Programming Language :: Python :: 3.9
Classifier: Programming Language :: Python :: 3.10
Classifier: Programming Language :: Python :: 3.11
Classifier: Programming Language :: Python :: 3.12
Requires-Dist: toml (>=0.10.2,<0.11.0)
Requires-Dist: xdg (>=6.0.0,<7.0.0)
